bydhvs/__init__.py
bydhvs-0.4.13.dist-info/licenses/LICENSE
bydhvs-0.4.13.dist-info/METADATA
bydhvs-0.4.13.dist-info/WHEEL
bydhvs-0.4.13.dist-info/top_level.txt
bydhvs-0.4.13.dist-info/RECORD
