Metadata-Version: 2.4
Name: bydhvs
Version: 0.4.13
Summary: A module for communicating with the BYD HVS Battery system
Author-email: bbr111 <ben1@gmx.net>
License: GPL-3.0
Project-URL: HomePage, https://github.com/bbr111/python-bydhvs
Project-URL: DOWNLOAD, https://github.com/bbr111/python-bydhvs/releases
Classifier: Development Status :: 3 - Alpha
Classifier: Environment :: Console
Classifier: Intended Audience :: Developers
Classifier: License :: OSI Approved :: GNU General Public License v3 (GPLv3)
Classifier: Operating System :: MacOS :: MacOS X
Classifier: Operating System :: Microsoft :: Windows
Classifier: Operating System :: POSIX
Classifier: Programming Language :: Python :: 3.9
Classifier: Programming Language :: Python :: 3.10
Classifier: Programming Language :: Python :: 3.11
Classifier: Programming Language :: Python :: 3.12
Classifier: Programming Language :: Python :: 3.13
Classifier: Topic :: Utilities
Requires-Python: >=3.9
License-File: LICENSE
Requires-Dist: crcmod>=1.7
Dynamic: license-file
